propar/__init__.py
propar/parameters.json
propar/parameters.py
bronkhorst_propar-1.2.0.dist-info/LICENSE
bronkhorst_propar-1.2.0.dist-info/METADATA
bronkhorst_propar-1.2.0.dist-info/WHEEL
bronkhorst_propar-1.2.0.dist-info/top_level.txt
bronkhorst_propar-1.2.0.dist-info/RECORD
