Metadata-Version: 2.1
Name: bronkhorst_propar
Version: 1.2.0
Summary: Communicate to Bronkhorst Instruments using the propar protocol over USB, RS232, or RS485.
Home-page: https://github.com/bronkhorst-developer/bronkhorst-propar
Author: Bronkhorst
Author-email: support@bronkhorst.com
Classifier: Programming Language :: Python :: 3
Classifier: License :: OSI Approved :: MIT License
Classifier: Operating System :: OS Independent
License-File: LICENSE
Requires-Dist: pyserial
